neosync/__init__.py
neosync/__init__.pyi
neosync/client.py
neosync/buf/validate/expression_pb2.py
neosync/buf/validate/validate_pb2.py
neosync/buf/validate/priv/private_pb2.py
neosync/mgmt/v1alpha1/account_hook_pb2.py
neosync/mgmt/v1alpha1/account_hook_pb2.pyi
neosync/mgmt/v1alpha1/account_hook_pb2_grpc.py
neosync/mgmt/v1alpha1/anonymization_pb2.py
neosync/mgmt/v1alpha1/anonymization_pb2.pyi
neosync/mgmt/v1alpha1/anonymization_pb2_grpc.py
neosync/mgmt/v1alpha1/api_key_pb2.py
neosync/mgmt/v1alpha1/api_key_pb2.pyi
neosync/mgmt/v1alpha1/api_key_pb2_grpc.py
neosync/mgmt/v1alpha1/auth_pb2.py
neosync/mgmt/v1alpha1/auth_pb2.pyi
neosync/mgmt/v1alpha1/auth_pb2_grpc.py
neosync/mgmt/v1alpha1/connection_data_pb2.py
neosync/mgmt/v1alpha1/connection_data_pb2.pyi
neosync/mgmt/v1alpha1/connection_data_pb2_grpc.py
neosync/mgmt/v1alpha1/connection_pb2.py
neosync/mgmt/v1alpha1/connection_pb2.pyi
neosync/mgmt/v1alpha1/connection_pb2_grpc.py
neosync/mgmt/v1alpha1/job_pb2.py
neosync/mgmt/v1alpha1/job_pb2.pyi
neosync/mgmt/v1alpha1/job_pb2_grpc.py
neosync/mgmt/v1alpha1/metrics_pb2.py
neosync/mgmt/v1alpha1/metrics_pb2.pyi
neosync/mgmt/v1alpha1/metrics_pb2_grpc.py
neosync/mgmt/v1alpha1/transformer_pb2.py
neosync/mgmt/v1alpha1/transformer_pb2.pyi
neosync/mgmt/v1alpha1/transformer_pb2_grpc.py
neosync/mgmt/v1alpha1/user_account_pb2.py
neosync/mgmt/v1alpha1/user_account_pb2.pyi
neosync/mgmt/v1alpha1/user_account_pb2_grpc.py
neosync-0.5.41.dist-info/METADATA
neosync-0.5.41.dist-info/WHEEL
neosync-0.5.41.dist-info/RECORD
